{
    "@schema": "https://raw.githubusercontent.com/slicer/slicer/master/Modules/Loadable/Markups/Resources/Schema/markups-schema-v1.0.3.json#",
    "markups": [
        {
            "type": "Curve",
            "coordinateSystem": "LPS",
            "coordinateUnits": "mm",
            "locked": false,
            "fixedNumberOfControlPoints": false,
            "labelFormat": "%N-%d",
            "lastUsedControlPointNumber": 33,
            "controlPoints": [
                {
                    "id": "1",
                    "label": "Centerline curve_2 (24)-1",
                    "description": "",
                    "associatedNodeID": "",
                    "position": [-73.83732849121106, 19.83563829994199, 10.881529809570282],
                    "orientation": [-1.0, -0.0, -0.0, -0.0, -1.0, -0.0, 0.0, 0.0, 1.0],
                    "selected": true,
                    "locked": false,
                    "visibility": false,
                    "positionStatus": "defined"
                },
                {
                    "id": "2",
                    "label": "Centerline curve_2 (24)-2",
                    "description": "",
                    "associatedNodeID": "",
                    "position": [-77.76774078369152, 23.294083610534643, 8.294203759765594],
                    "orientation": [-1.0, -0.0, -0.0, -0.0, -1.0, -0.0, 0.0, 0.0, 1.0],
                    "selected": true,
                    "locked": false,
                    "visibility": false,
                    "positionStatus": "defined"
                },
                {
                    "id": "3",
                    "label": "Centerline curve_2 (24)-3",
                    "description": "",
                    "associatedNodeID": "",
                    "position": [-77.94848114013684, 23.44479347801206, 8.183669091796844],
                    "orientation": [-1.0, -0.0, -0.0, -0.0, -1.0, -0.0, 0.0, 0.0, 1.0],
                    "selected": true,
                    "locked": false,
                    "visibility": false,
                    "positionStatus": "defined"
                },
                {
                    "id": "4",
                    "label": "Centerline curve_2 (24)-4",
                    "description": "",
                    "associatedNodeID": "",
                    "position": [-78.11403137207043, 23.572638526916479, 8.095992089843719],
                    "orientation": [-1.0, -0.0, -0.0, -0.0, -1.0, -0.0, 0.0, 0.0, 1.0],
                    "selected": true,
                    "locked": false,
                    "visibility": false,
                    "positionStatus": "defined"
                },
                {
                    "id": "5",
                    "label": "Centerline curve_2 (24)-5",
                    "description": "",
                    "associatedNodeID": "",
                    "position": [-78.26030975341809, 23.674001947402929, 8.029669763183563],
                    "orientation": [-1.0, -0.0, -0.0, -0.0, -1.0, -0.0, 0.0, 0.0, 1.0],
                    "selected": true,
                    "locked": false,
                    "visibility": false,
                    "positionStatus": "defined"
                },
                {
                    "id": "6",
                    "label": "Centerline curve_2 (24)-6",
                    "description": "",
                    "associatedNodeID": "",
                    "position": [-78.39995819091809, 23.759645954132055, 7.972250939941375],
                    "orientation": [-1.0, -0.0, -0.0, -0.0, -1.0, -0.0, 0.0, 0.0, 1.0],
                    "selected": true,
                    "locked": false,
                    "visibility": false,
                    "positionStatus": "defined"
                },
                {
                    "id": "7",
                    "label": "Centerline curve_2 (24)-7",
                    "description": "",
                    "associatedNodeID": "",
                    "position": [-78.54558807373059, 23.840333477020239, 7.911299707031219],
                    "orientation": [-1.0, -0.0, -0.0, -0.0, -1.0, -0.0, 0.0, 0.0, 1.0],
                    "selected": true,
                    "locked": false,
                    "visibility": false,
                    "positionStatus": "defined"
                },
                {
                    "id": "8",
                    "label": "Centerline curve_2 (24)-8",
                    "description": "",
                    "associatedNodeID": "",
                    "position": [-78.70651489257824, 23.925494209289526, 7.837904931640594],
                    "orientation": [-1.0, -0.0, -0.0, -0.0, -1.0, -0.0, 0.0, 0.0, 1.0],
                    "selected": true,
                    "locked": false,
                    "visibility": false,
                    "positionStatus": "defined"
                },
                {
                    "id": "9",
                    "label": "Centerline curve_2 (24)-9",
                    "description": "",
                    "associatedNodeID": "",
                    "position": [-78.87676483154309, 24.018466964721655, 7.759558679199188],
                    "orientation": [-1.0, -0.0, -0.0, -0.0, -1.0, -0.0, 0.0, 0.0, 1.0],
                    "selected": true,
                    "locked": false,
                    "visibility": false,
                    "positionStatus": "defined"
                },
                {
                    "id": "10",
                    "label": "Centerline curve_2 (24)-10",
                    "description": "",
                    "associatedNodeID": "",
                    "position": [-79.04610687255871, 24.120762363433813, 7.6882619873046569],
                    "orientation": [-1.0, -0.0, -0.0, -0.0, -1.0, -0.0, 0.0, 0.0, 1.0],
                    "selected": true,
                    "locked": false,
                    "visibility": false,
                    "positionStatus": "defined"
                },
                {
                    "id": "11",
                    "label": "Centerline curve_2 (24)-11",
                    "description": "",
                    "associatedNodeID": "",
                    "position": [-79.20962768554699, 24.232163921356177, 7.627692224121063],
                    "orientation": [-1.0, -0.0, -0.0, -0.0, -1.0, -0.0, 0.0, 0.0, 1.0],
                    "selected": true,
                    "locked": false,
                    "visibility": false,
                    "positionStatus": "defined"
                },
                {
                    "id": "12",
                    "label": "Centerline curve_2 (24)-12",
                    "description": "",
                    "associatedNodeID": "",
                    "position": [-79.36764770507824, 24.350627914428686, 7.5730886474609069],
                    "orientation": [-1.0, -0.0, -0.0, -0.0, -1.0, -0.0, 0.0, 0.0, 1.0],
                    "selected": true,
                    "locked": false,
                    "visibility": false,
                    "positionStatus": "defined"
                },
                {
                    "id": "13",
                    "label": "Centerline curve_2 (24)-13",
                    "description": "",
                    "associatedNodeID": "",
                    "position": [-79.52073150634777, 24.474019065856909, 7.5192861572265319],
                    "orientation": [-1.0, -0.0, -0.0, -0.0, -1.0, -0.0, 0.0, 0.0, 1.0],
                    "selected": true,
                    "locked": false,
                    "visibility": false,
                    "positionStatus": "defined"
                },
                {
                    "id": "14",
                    "label": "Centerline curve_2 (24)-14",
                    "description": "",
                    "associatedNodeID": "",
                    "position": [-79.66945129394543, 24.60020209884641, 7.4611196533202819],
                    "orientation": [-1.0, -0.0, -0.0, -0.0, -1.0, -0.0, 0.0, 0.0, 1.0],
                    "selected": true,
                    "locked": false,
                    "visibility": false,
                    "positionStatus": "defined"
                },
                {
                    "id": "15",
                    "label": "Centerline curve_2 (24)-15",
                    "description": "",
                    "associatedNodeID": "",
                    "position": [-79.81463104248059, 24.72684718704221, 7.3936681762695],
                    "orientation": [-1.0, -0.0, -0.0, -0.0, -1.0, -0.0, 0.0, 0.0, 1.0],
                    "selected": true,
                    "locked": false,
                    "visibility": false,
                    "positionStatus": "defined"
                },
                {
                    "id": "16",
                    "label": "Centerline curve_2 (24)-16",
                    "description": "",
                    "associatedNodeID": "",
                    "position": [-79.96328979492199, 24.84809495544431, 7.3220205322265319],
                    "orientation": [-1.0, -0.0, -0.0, -0.0, -1.0, -0.0, 0.0, 0.0, 1.0],
                    "selected": true,
                    "locked": false,
                    "visibility": false,
                    "positionStatus": "defined"
                },
                {
                    "id": "17",
                    "label": "Centerline curve_2 (24)-17",
                    "description": "",
                    "associatedNodeID": "",
                    "position": [-80.10917907714856, 24.97013618087766, 7.2452306762695],
                    "orientation": [-1.0, -0.0, -0.0, -0.0, -1.0, -0.0, 0.0, 0.0, 1.0],
                    "selected": true,
                    "locked": false,
                    "visibility": false,
                    "positionStatus": "defined"
                },
                {
                    "id": "18",
                    "label": "Centerline curve_2 (24)-18",
                    "description": "",
                    "associatedNodeID": "",
                    "position": [-80.25503021240246, 25.09020806884763, 7.165717126464813],
                    "orientation": [-1.0, -0.0, -0.0, -0.0, -1.0, -0.0, 0.0, 0.0, 1.0],
                    "selected": true,
                    "locked": false,
                    "visibility": false,
                    "positionStatus": "defined"
                },
                {
                    "id": "19",
                    "label": "Centerline curve_2 (24)-19",
                    "description": "",
                    "associatedNodeID": "",
                    "position": [-80.40404754638684, 25.20508147811887, 7.086249353027313],
                    "orientation": [-1.0, -0.0, -0.0, -0.0, -1.0, -0.0, 0.0, 0.0, 1.0],
                    "selected": true,
                    "locked": false,
                    "visibility": false,
                    "positionStatus": "defined"
                },
                {
                    "id": "20",
                    "label": "Centerline curve_2 (24)-20",
                    "description": "",
                    "associatedNodeID": "",
                    "position": [-80.55913024902356, 25.31198598480222, 7.0094900146484069],
                    "orientation": [-1.0, -0.0, -0.0, -0.0, -1.0, -0.0, 0.0, 0.0, 1.0],
                    "selected": true,
                    "locked": false,
                    "visibility": false,
                    "positionStatus": "defined"
                },
                {
                    "id": "21",
                    "label": "Centerline curve_2 (24)-21",
                    "description": "",
                    "associatedNodeID": "",
                    "position": [-80.72102600097668, 25.411574855804419, 6.937277795410125],
                    "orientation": [-1.0, -0.0, -0.0, -0.0, -1.0, -0.0, 0.0, 0.0, 1.0],
                    "selected": true,
                    "locked": false,
                    "visibility": false,
                    "positionStatus": "defined"
                },
                {
                    "id": "22",
                    "label": "Centerline curve_2 (24)-22",
                    "description": "",
                    "associatedNodeID": "",
                    "position": [-80.88791900634777, 25.50629521942136, 6.870009423828094],
                    "orientation": [-1.0, -0.0, -0.0, -0.0, -1.0, -0.0, 0.0, 0.0, 1.0],
                    "selected": true,
                    "locked": false,
                    "visibility": false,
                    "positionStatus": "defined"
                },
                {
                    "id": "23",
                    "label": "Centerline curve_2 (24)-23",
                    "description": "",
                    "associatedNodeID": "",
                    "position": [-81.05798583984387, 25.598971858978247, 6.808020593261688],
                    "orientation": [-1.0, -0.0, -0.0, -0.0, -1.0, -0.0, 0.0, 0.0, 1.0],
                    "selected": true,
                    "locked": false,
                    "visibility": false,
                    "positionStatus": "defined"
                },
                {
                    "id": "24",
                    "label": "Centerline curve_2 (24)-24",
                    "description": "",
                    "associatedNodeID": "",
                    "position": [-81.2293572998048, 25.69247628784177, 6.75163936767575],
                    "orientation": [-1.0, -0.0, -0.0, -0.0, -1.0, -0.0, 0.0, 0.0, 1.0],
                    "selected": true,
                    "locked": false,
                    "visibility": false,
                    "positionStatus": "defined"
                },
                {
                    "id": "25",
                    "label": "Centerline curve_2 (24)-25",
                    "description": "",
                    "associatedNodeID": "",
                    "position": [-81.40016418457043, 25.789728656768774, 6.701239587402313],
                    "orientation": [-1.0, -0.0, -0.0, -0.0, -1.0, -0.0, 0.0, 0.0, 1.0],
                    "selected": true,
                    "locked": false,
                    "visibility": false,
                    "positionStatus": "defined"
                },
                {
                    "id": "26",
                    "label": "Centerline curve_2 (24)-26",
                    "description": "",
                    "associatedNodeID": "",
                    "position": [-81.56878906250012, 25.89322616195676, 6.6559743896484069],
                    "orientation": [-1.0, -0.0, -0.0, -0.0, -1.0, -0.0, 0.0, 0.0, 1.0],
                    "selected": true,
                    "locked": false,
                    "visibility": false,
                    "positionStatus": "defined"
                },
                {
                    "id": "27",
                    "label": "Centerline curve_2 (24)-27",
                    "description": "",
                    "associatedNodeID": "",
                    "position": [-81.73297363281262, 26.003666416168188, 6.6016225830077819],
                    "orientation": [-1.0, -0.0, -0.0, -0.0, -1.0, -0.0, 0.0, 0.0, 1.0],
                    "selected": true,
                    "locked": false,
                    "visibility": false,
                    "positionStatus": "defined"
                },
                {
                    "id": "28",
                    "label": "Centerline curve_2 (24)-28",
                    "description": "",
                    "associatedNodeID": "",
                    "position": [-81.88910919189465, 26.1213545951843, 6.532919885253875],
                    "orientation": [-1.0, -0.0, -0.0, -0.0, -1.0, -0.0, 0.0, 0.0, 1.0],
                    "selected": true,
                    "locked": false,
                    "visibility": false,
                    "positionStatus": "defined"
                },
                {
                    "id": "29",
                    "label": "Centerline curve_2 (24)-29",
                    "description": "",
                    "associatedNodeID": "",
                    "position": [-82.0327249145509, 26.245839134216284, 6.466589929199188],
                    "orientation": [-1.0, -0.0, -0.0, -0.0, -1.0, -0.0, 0.0, 0.0, 1.0],
                    "selected": true,
                    "locked": false,
                    "visibility": false,
                    "positionStatus": "defined"
                },
                {
                    "id": "30",
                    "label": "Centerline curve_2 (24)-30",
                    "description": "",
                    "associatedNodeID": "",
                    "position": [-82.16466766357434, 26.374214664459204, 6.418951989746063],
                    "orientation": [-1.0, -0.0, -0.0, -0.0, -1.0, -0.0, 0.0, 0.0, 1.0],
                    "selected": true,
                    "locked": false,
                    "visibility": false,
                    "positionStatus": "defined"
                },
                {
                    "id": "31",
                    "label": "Centerline curve_2 (24)-31",
                    "description": "",
                    "associatedNodeID": "",
                    "position": [-82.31135803222668, 26.51890613174436, 6.387770654296844],
                    "orientation": [-1.0, -0.0, -0.0, -0.0, -1.0, -0.0, 0.0, 0.0, 1.0],
                    "selected": true,
                    "locked": false,
                    "visibility": false,
                    "positionStatus": "defined"
                },
                {
                    "id": "32",
                    "label": "Centerline curve_2 (24)-32",
                    "description": "",
                    "associatedNodeID": "",
                    "position": [-82.44571929931652, 26.657041088104223, 6.366309167480438],
                    "orientation": [-1.0, -0.0, -0.0, -0.0, -1.0, -0.0, 0.0, 0.0, 1.0],
                    "selected": true,
                    "locked": false,
                    "visibility": false,
                    "positionStatus": "defined"
                },
                {
                    "id": "33",
                    "label": "Centerline curve_2 (24)-33",
                    "description": "",
                    "associatedNodeID": "",
                    "position": [-83.9383645629884, 27.88001348114011, 5.899420739746063],
                    "orientation": [-1.0, -0.0, -0.0, -0.0, -1.0, -0.0, 0.0, 0.0, 1.0],
                    "selected": true,
                    "locked": false,
                    "visibility": false,
                    "positionStatus": "defined"
                }
            ],
            "measurements": [
                {
                    "name": "length",
                    "enabled": false,
                    "units": "mm",
                    "printFormat": "%-#4.4g%s"
                },
                {
                    "name": "curvature mean",
                    "enabled": false,
                    "printFormat": "%5.3f %s"
                },
                {
                    "name": "curvature max",
                    "enabled": false,
                    "printFormat": "%5.3f %s"
                },
                {
                    "name": "Radius",
                    "enabled": true,
                    "units": "mm",
                    "printFormat": "%5.3f %s",
                    "controlPointValues": [
                        6.206182881561125,
                        4.42170079012014,
                        4.4023805669572699,
                        4.385683437896497,
                        4.368986308835725,
                        4.352289179774952,
                        4.33559205071418,
                        4.334957355030036,
                        4.334414599531893,
                        4.3363494556234,
                        4.3401526657307889,
                        4.343955875838178,
                        4.347759085945567,
                        4.351562296052957,
                        4.357371569226278,
                        4.38579454364656,
                        4.41421751806684,
                        4.442640492487122,
                        4.471063466907403,
                        4.490736522451961,
                        4.508668144778987,
                        4.526599767106013,
                        4.54453138943304,
                        4.562463011760065,
                        4.580394634087092,
                        4.604252131104595,
                        4.625297400823607,
                        4.637690948321435,
                        4.650084495819263,
                        4.649364902641772,
                        4.644833605365058,
                        4.640439436336515,
                        4.640439436336515
                    ]
                }
            ],
            "display": {
                "visibility": false,
                "opacity": 1.0,
                "color": [0.4, 1.0, 0.0],
                "selectedColor": [0.145098, 0.607843, 0.709804],
                "activeColor": [0.4, 1.0, 0.0],
                "propertiesLabelVisibility": true,
                "pointLabelsVisibility": false,
                "textScale": 3.0,
                "glyphType": "Sphere3D",
                "glyphScale": 1.0,
                "glyphSize": 5.0,
                "useGlyphScale": true,
                "sliceProjection": false,
                "sliceProjectionUseFiducialColor": true,
                "sliceProjectionOutlinedBehindSlicePlane": false,
                "sliceProjectionColor": [1.0, 1.0, 1.0],
                "sliceProjectionOpacity": 0.6,
                "lineThickness": 0.2,
                "lineColorFadingStart": 1.0,
                "lineColorFadingEnd": 10.0,
                "lineColorFadingSaturation": 1.0,
                "lineColorFadingHueOffset": 0.0,
                "handlesInteractive": false,
                "translationHandleVisibility": true,
                "rotationHandleVisibility": true,
                "scaleHandleVisibility": true,
                "interactionHandleScale": 3.0,
                "snapMode": "toVisibleSurface"
            }
        }
    ]
}