{
    "@schema": "https://raw.githubusercontent.com/slicer/slicer/master/Modules/Loadable/Markups/Resources/Schema/markups-schema-v1.0.3.json#",
    "markups": [
        {
            "type": "Curve",
            "coordinateSystem": "LPS",
            "coordinateUnits": "mm",
            "locked": false,
            "fixedNumberOfControlPoints": false,
            "labelFormat": "%N-%d",
            "lastUsedControlPointNumber": 40,
            "controlPoints": [
                {
                    "id": "1",
                    "label": "Centerline curve_3 (0)-1",
                    "description": "",
                    "associatedNodeID": "",
                    "position": [-71.20819091796875, 3.0200891494750978, 12.775374412536621],
                    "orientation": [-1.0, -0.0, -0.0, -0.0, -1.0, -0.0, 0.0, 0.0, 1.0],
                    "selected": true,
                    "locked": false,
                    "visibility": false,
                    "positionStatus": "defined"
                },
                {
                    "id": "2",
                    "label": "Centerline curve_3 (0)-2",
                    "description": "",
                    "associatedNodeID": "",
                    "position": [-71.01815032958985, 2.986356735229492, 12.728777885437012],
                    "orientation": [-1.0, -0.0, -0.0, -0.0, -1.0, -0.0, 0.0, 0.0, 1.0],
                    "selected": true,
                    "locked": false,
                    "visibility": false,
                    "positionStatus": "defined"
                },
                {
                    "id": "3",
                    "label": "Centerline curve_3 (0)-3",
                    "description": "",
                    "associatedNodeID": "",
                    "position": [-70.82881927490235, 2.9123542308807375, 12.72154712677002],
                    "orientation": [-1.0, -0.0, -0.0, -0.0, -1.0, -0.0, 0.0, 0.0, 1.0],
                    "selected": true,
                    "locked": false,
                    "visibility": false,
                    "positionStatus": "defined"
                },
                {
                    "id": "4",
                    "label": "Centerline curve_3 (0)-4",
                    "description": "",
                    "associatedNodeID": "",
                    "position": [-70.6500473022461, 2.838789939880371, 12.663479804992676],
                    "orientation": [-1.0, -0.0, -0.0, -0.0, -1.0, -0.0, 0.0, 0.0, 1.0],
                    "selected": true,
                    "locked": false,
                    "visibility": false,
                    "positionStatus": "defined"
                },
                {
                    "id": "5",
                    "label": "Centerline curve_3 (0)-5",
                    "description": "",
                    "associatedNodeID": "",
                    "position": [-70.4719467163086, 2.7428507804870607, 12.643770217895508],
                    "orientation": [-1.0, -0.0, -0.0, -0.0, -1.0, -0.0, 0.0, 0.0, 1.0],
                    "selected": true,
                    "locked": false,
                    "visibility": false,
                    "positionStatus": "defined"
                },
                {
                    "id": "6",
                    "label": "Centerline curve_3 (0)-6",
                    "description": "",
                    "associatedNodeID": "",
                    "position": [-70.30486297607422, 2.6272122859954836, 12.625110626220704],
                    "orientation": [-1.0, -0.0, -0.0, -0.0, -1.0, -0.0, 0.0, 0.0, 1.0],
                    "selected": true,
                    "locked": false,
                    "visibility": false,
                    "positionStatus": "defined"
                },
                {
                    "id": "7",
                    "label": "Centerline curve_3 (0)-7",
                    "description": "",
                    "associatedNodeID": "",
                    "position": [-70.1388931274414, 2.5270254611968996, 12.571475982666016],
                    "orientation": [-1.0, -0.0, -0.0, -0.0, -1.0, -0.0, 0.0, 0.0, 1.0],
                    "selected": true,
                    "locked": false,
                    "visibility": false,
                    "positionStatus": "defined"
                },
                {
                    "id": "8",
                    "label": "Centerline curve_3 (0)-8",
                    "description": "",
                    "associatedNodeID": "",
                    "position": [-69.97611999511719, 2.4153828620910646, 12.52600383758545],
                    "orientation": [-1.0, -0.0, -0.0, -0.0, -1.0, -0.0, 0.0, 0.0, 1.0],
                    "selected": true,
                    "locked": false,
                    "visibility": false,
                    "positionStatus": "defined"
                },
                {
                    "id": "9",
                    "label": "Centerline curve_3 (0)-9",
                    "description": "",
                    "associatedNodeID": "",
                    "position": [-69.82709503173828, 2.2937800884246828, 12.465007781982422],
                    "orientation": [-1.0, -0.0, -0.0, -0.0, -1.0, -0.0, 0.0, 0.0, 1.0],
                    "selected": true,
                    "locked": false,
                    "visibility": false,
                    "positionStatus": "defined"
                },
                {
                    "id": "10",
                    "label": "Centerline curve_3 (0)-10",
                    "description": "",
                    "associatedNodeID": "",
                    "position": [-69.6860122680664, 2.1707518100738527, 12.393133163452149],
                    "orientation": [-1.0, -0.0, -0.0, -0.0, -1.0, -0.0, 0.0, 0.0, 1.0],
                    "selected": true,
                    "locked": false,
                    "visibility": false,
                    "positionStatus": "defined"
                },
                {
                    "id": "11",
                    "label": "Centerline curve_3 (0)-11",
                    "description": "",
                    "associatedNodeID": "",
                    "position": [-69.53998565673828, 2.0518381595611574, 12.31618881225586],
                    "orientation": [-1.0, -0.0, -0.0, -0.0, -1.0, -0.0, 0.0, 0.0, 1.0],
                    "selected": true,
                    "locked": false,
                    "visibility": false,
                    "positionStatus": "defined"
                },
                {
                    "id": "12",
                    "label": "Centerline curve_3 (0)-12",
                    "description": "",
                    "associatedNodeID": "",
                    "position": [-69.37847900390625, 1.9444084167480469, 12.235631942749024],
                    "orientation": [-1.0, -0.0, -0.0, -0.0, -1.0, -0.0, 0.0, 0.0, 1.0],
                    "selected": true,
                    "locked": false,
                    "visibility": false,
                    "positionStatus": "defined"
                },
                {
                    "id": "13",
                    "label": "Centerline curve_3 (0)-13",
                    "description": "",
                    "associatedNodeID": "",
                    "position": [-69.26583099365235, 1.8278721570968629, 12.124018669128418],
                    "orientation": [-1.0, -0.0, -0.0, -0.0, -1.0, -0.0, 0.0, 0.0, 1.0],
                    "selected": true,
                    "locked": false,
                    "visibility": false,
                    "positionStatus": "defined"
                },
                {
                    "id": "14",
                    "label": "Centerline curve_3 (0)-14",
                    "description": "",
                    "associatedNodeID": "",
                    "position": [-69.18855285644531, 1.6991262435913087, 11.98936653137207],
                    "orientation": [-1.0, -0.0, -0.0, -0.0, -1.0, -0.0, 0.0, 0.0, 1.0],
                    "selected": true,
                    "locked": false,
                    "visibility": false,
                    "positionStatus": "defined"
                },
                {
                    "id": "15",
                    "label": "Centerline curve_3 (0)-15",
                    "description": "",
                    "associatedNodeID": "",
                    "position": [-69.06898498535156, 1.5924534797668458, 11.86282730102539],
                    "orientation": [-1.0, -0.0, -0.0, -0.0, -1.0, -0.0, 0.0, 0.0, 1.0],
                    "selected": true,
                    "locked": false,
                    "visibility": false,
                    "positionStatus": "defined"
                },
                {
                    "id": "16",
                    "label": "Centerline curve_3 (0)-16",
                    "description": "",
                    "associatedNodeID": "",
                    "position": [-68.93475341796875, 1.4906909465789796, 11.743826866149903],
                    "orientation": [-1.0, -0.0, -0.0, -0.0, -1.0, -0.0, 0.0, 0.0, 1.0],
                    "selected": true,
                    "locked": false,
                    "visibility": false,
                    "positionStatus": "defined"
                },
                {
                    "id": "17",
                    "label": "Centerline curve_3 (0)-17",
                    "description": "",
                    "associatedNodeID": "",
                    "position": [-68.81453704833985, 1.3698761463165284, 11.636283874511719],
                    "orientation": [-1.0, -0.0, -0.0, -0.0, -1.0, -0.0, 0.0, 0.0, 1.0],
                    "selected": true,
                    "locked": false,
                    "visibility": false,
                    "positionStatus": "defined"
                },
                {
                    "id": "18",
                    "label": "Centerline curve_3 (0)-18",
                    "description": "",
                    "associatedNodeID": "",
                    "position": [-68.72195434570313, 1.2177730798721314, 11.543062210083008],
                    "orientation": [-1.0, -0.0, -0.0, -0.0, -1.0, -0.0, 0.0, 0.0, 1.0],
                    "selected": true,
                    "locked": false,
                    "visibility": false,
                    "positionStatus": "defined"
                },
                {
                    "id": "19",
                    "label": "Centerline curve_3 (0)-19",
                    "description": "",
                    "associatedNodeID": "",
                    "position": [-68.60166931152344, 1.0920827388763428, 11.44174575805664],
                    "orientation": [-1.0, -0.0, -0.0, -0.0, -1.0, -0.0, 0.0, 0.0, 1.0],
                    "selected": true,
                    "locked": false,
                    "visibility": false,
                    "positionStatus": "defined"
                },
                {
                    "id": "20",
                    "label": "Centerline curve_3 (0)-20",
                    "description": "",
                    "associatedNodeID": "",
                    "position": [-68.46372985839844, 0.9922887682914734, 11.323918342590332],
                    "orientation": [-1.0, -0.0, -0.0, -0.0, -1.0, -0.0, 0.0, 0.0, 1.0],
                    "selected": true,
                    "locked": false,
                    "visibility": false,
                    "positionStatus": "defined"
                },
                {
                    "id": "21",
                    "label": "Centerline curve_3 (0)-21",
                    "description": "",
                    "associatedNodeID": "",
                    "position": [-68.32356262207031, 0.897689700126648, 11.20258903503418],
                    "orientation": [-1.0, -0.0, -0.0, -0.0, -1.0, -0.0, 0.0, 0.0, 1.0],
                    "selected": true,
                    "locked": false,
                    "visibility": false,
                    "positionStatus": "defined"
                },
                {
                    "id": "22",
                    "label": "Centerline curve_3 (0)-22",
                    "description": "",
                    "associatedNodeID": "",
                    "position": [-68.19657897949219, 0.7875649333000183, 11.090797424316407],
                    "orientation": [-1.0, -0.0, -0.0, -0.0, -1.0, -0.0, 0.0, 0.0, 1.0],
                    "selected": true,
                    "locked": false,
                    "visibility": false,
                    "positionStatus": "defined"
                },
                {
                    "id": "23",
                    "label": "Centerline curve_3 (0)-23",
                    "description": "",
                    "associatedNodeID": "",
                    "position": [-68.09700012207031, 0.6424058079719544, 11.000895500183106],
                    "orientation": [-1.0, -0.0, -0.0, -0.0, -1.0, -0.0, 0.0, 0.0, 1.0],
                    "selected": true,
                    "locked": false,
                    "visibility": false,
                    "positionStatus": "defined"
                },
                {
                    "id": "24",
                    "label": "Centerline curve_3 (0)-24",
                    "description": "",
                    "associatedNodeID": "",
                    "position": [-68.00199127197266, 0.4903791844844818, 10.911799430847168],
                    "orientation": [-1.0, -0.0, -0.0, -0.0, -1.0, -0.0, 0.0, 0.0, 1.0],
                    "selected": true,
                    "locked": false,
                    "visibility": false,
                    "positionStatus": "defined"
                },
                {
                    "id": "25",
                    "label": "Centerline curve_3 (0)-25",
                    "description": "",
                    "associatedNodeID": "",
                    "position": [-67.90017700195313, 0.35548126697540285, 10.800235748291016],
                    "orientation": [-1.0, -0.0, -0.0, -0.0, -1.0, -0.0, 0.0, 0.0, 1.0],
                    "selected": true,
                    "locked": false,
                    "visibility": false,
                    "positionStatus": "defined"
                },
                {
                    "id": "26",
                    "label": "Centerline curve_3 (0)-26",
                    "description": "",
                    "associatedNodeID": "",
                    "position": [-67.7785873413086, 0.23194661736488343, 10.69270133972168],
                    "orientation": [-1.0, -0.0, -0.0, -0.0, -1.0, -0.0, 0.0, 0.0, 1.0],
                    "selected": true,
                    "locked": false,
                    "visibility": false,
                    "positionStatus": "defined"
                },
                {
                    "id": "27",
                    "label": "Centerline curve_3 (0)-27",
                    "description": "",
                    "associatedNodeID": "",
                    "position": [-67.64755249023438, 0.10713514685630799, 10.606308937072754],
                    "orientation": [-1.0, -0.0, -0.0, -0.0, -1.0, -0.0, 0.0, 0.0, 1.0],
                    "selected": true,
                    "locked": false,
                    "visibility": false,
                    "positionStatus": "defined"
                },
                {
                    "id": "28",
                    "label": "Centerline curve_3 (0)-28",
                    "description": "",
                    "associatedNodeID": "",
                    "position": [-67.516357421875, -0.02992846816778183, 10.543842315673829],
                    "orientation": [-1.0, -0.0, -0.0, -0.0, -1.0, -0.0, 0.0, 0.0, 1.0],
                    "selected": true,
                    "locked": false,
                    "visibility": false,
                    "positionStatus": "defined"
                },
                {
                    "id": "29",
                    "label": "Centerline curve_3 (0)-29",
                    "description": "",
                    "associatedNodeID": "",
                    "position": [-67.37618255615235, -0.16216905415058137, 10.4832124710083],
                    "orientation": [-1.0, -0.0, -0.0, -0.0, -1.0, -0.0, 0.0, 0.0, 1.0],
                    "selected": true,
                    "locked": false,
                    "visibility": false,
                    "positionStatus": "defined"
                },
                {
                    "id": "30",
                    "label": "Centerline curve_3 (0)-30",
                    "description": "",
                    "associatedNodeID": "",
                    "position": [-67.2450942993164, -0.30499523878097536, 10.425021171569825],
                    "orientation": [-1.0, -0.0, -0.0, -0.0, -1.0, -0.0, 0.0, 0.0, 1.0],
                    "selected": true,
                    "locked": false,
                    "visibility": false,
                    "positionStatus": "defined"
                },
                {
                    "id": "31",
                    "label": "Centerline curve_3 (0)-31",
                    "description": "",
                    "associatedNodeID": "",
                    "position": [-67.12163543701172, -0.44250422716140749, 10.348831176757813],
                    "orientation": [-1.0, -0.0, -0.0, -0.0, -1.0, -0.0, 0.0, 0.0, 1.0],
                    "selected": true,
                    "locked": false,
                    "visibility": false,
                    "positionStatus": "defined"
                },
                {
                    "id": "32",
                    "label": "Centerline curve_3 (0)-32",
                    "description": "",
                    "associatedNodeID": "",
                    "position": [-66.98539733886719, -0.5699474811553955, 10.272939682006836],
                    "orientation": [-1.0, -0.0, -0.0, -0.0, -1.0, -0.0, 0.0, 0.0, 1.0],
                    "selected": true,
                    "locked": false,
                    "visibility": false,
                    "positionStatus": "defined"
                },
                {
                    "id": "33",
                    "label": "Centerline curve_3 (0)-33",
                    "description": "",
                    "associatedNodeID": "",
                    "position": [-66.84466552734375, -0.6836512684822083, 10.180142402648926],
                    "orientation": [-1.0, -0.0, -0.0, -0.0, -1.0, -0.0, 0.0, 0.0, 1.0],
                    "selected": true,
                    "locked": false,
                    "visibility": false,
                    "positionStatus": "defined"
                },
                {
                    "id": "34",
                    "label": "Centerline curve_3 (0)-34",
                    "description": "",
                    "associatedNodeID": "",
                    "position": [-66.7037124633789, -0.7822589874267578, 10.072805404663086],
                    "orientation": [-1.0, -0.0, -0.0, -0.0, -1.0, -0.0, 0.0, 0.0, 1.0],
                    "selected": true,
                    "locked": false,
                    "visibility": false,
                    "positionStatus": "defined"
                },
                {
                    "id": "35",
                    "label": "Centerline curve_3 (0)-35",
                    "description": "",
                    "associatedNodeID": "",
                    "position": [-66.57209777832031, -0.8927077651023865, 9.989094734191895],
                    "orientation": [-1.0, -0.0, -0.0, -0.0, -1.0, -0.0, 0.0, 0.0, 1.0],
                    "selected": true,
                    "locked": false,
                    "visibility": false,
                    "positionStatus": "defined"
                },
                {
                    "id": "36",
                    "label": "Centerline curve_3 (0)-36",
                    "description": "",
                    "associatedNodeID": "",
                    "position": [-66.44181060791016, -1.020928978919983, 9.914353370666504],
                    "orientation": [-1.0, -0.0, -0.0, -0.0, -1.0, -0.0, 0.0, 0.0, 1.0],
                    "selected": true,
                    "locked": false,
                    "visibility": false,
                    "positionStatus": "defined"
                },
                {
                    "id": "37",
                    "label": "Centerline curve_3 (0)-37",
                    "description": "",
                    "associatedNodeID": "",
                    "position": [-66.29359436035156, -1.1566749811172486, 9.810593605041504],
                    "orientation": [-1.0, -0.0, -0.0, -0.0, -1.0, -0.0, 0.0, 0.0, 1.0],
                    "selected": true,
                    "locked": false,
                    "visibility": false,
                    "positionStatus": "defined"
                },
                {
                    "id": "38",
                    "label": "Centerline curve_3 (0)-38",
                    "description": "",
                    "associatedNodeID": "",
                    "position": [-66.14592742919922, -1.2774536609649659, 9.695971488952637],
                    "orientation": [-1.0, -0.0, -0.0, -0.0, -1.0, -0.0, 0.0, 0.0, 1.0],
                    "selected": true,
                    "locked": false,
                    "visibility": false,
                    "positionStatus": "defined"
                },
                {
                    "id": "39",
                    "label": "Centerline curve_3 (0)-39",
                    "description": "",
                    "associatedNodeID": "",
                    "position": [-66.04727172851563, -1.3491566181182862, 9.609984397888184],
                    "orientation": [-1.0, -0.0, -0.0, -0.0, -1.0, -0.0, 0.0, 0.0, 1.0],
                    "selected": true,
                    "locked": false,
                    "visibility": false,
                    "positionStatus": "defined"
                },
                {
                    "id": "40",
                    "label": "Centerline curve_3 (0)-40",
                    "description": "",
                    "associatedNodeID": "",
                    "position": [-65.21929931640625, -2.276376485824585, 8.87733268737793],
                    "orientation": [-1.0, -0.0, -0.0, -0.0, -1.0, -0.0, 0.0, 0.0, 1.0],
                    "selected": true,
                    "locked": false,
                    "visibility": false,
                    "positionStatus": "defined"
                }
            ],
            "measurements": [
                {
                    "name": "length",
                    "enabled": false,
                    "units": "mm",
                    "printFormat": "%-#4.4g%s"
                },
                {
                    "name": "curvature mean",
                    "enabled": false,
                    "printFormat": "%5.3f %s"
                },
                {
                    "name": "curvature max",
                    "enabled": false,
                    "printFormat": "%5.3f %s"
                },
                {
                    "name": "Radius",
                    "enabled": true,
                    "units": "mm",
                    "controlPointValues": [
                        0.2942683705568964,
                        0.43705305526072266,
                        0.5747016302070074,
                        0.7138194417343644,
                        0.837614450584917,
                        0.9614094594354697,
                        1.088809403120755,
                        1.2058319392215276,
                        1.318013421806187,
                        1.4034720369149559,
                        1.454437148834648,
                        1.5195329962380593,
                        1.580970000508994,
                        1.6060354215696613,
                        1.6539285190156426,
                        1.701821616461624,
                        1.7497147139076055,
                        1.804406147750252,
                        1.8934177488418396,
                        1.9830274606529908,
                        2.072637172464142,
                        2.1622468842752937,
                        2.2517552821676105,
                        2.340141612409112,
                        2.42770486354553,
                        2.5121958130354535,
                        2.58680372228634,
                        2.6495807953708416,
                        2.7108874355635,
                        2.7721940757561587,
                        2.8138541323770935,
                        2.8499716813773978,
                        2.8826791167141248,
                        2.9099311019572995,
                        2.9124105848000254,
                        2.9068134146772537,
                        2.9024007824395117,
                        2.898364618514762,
                        2.8943284545900127,
                        2.8943284545900127
                    ]
                }
            ],
            "display": {
                "visibility": true,
                "opacity": 1.0,
                "color": [0.4, 1.0, 0.0],
                "selectedColor": [1.0, 0.5000076295109484, 0.5000076295109484],
                "activeColor": [0.4, 1.0, 0.0],
                "propertiesLabelVisibility": true,
                "pointLabelsVisibility": false,
                "textScale": 3.0,
                "glyphType": "Sphere3D",
                "glyphScale": 1.0,
                "glyphSize": 5.0,
                "useGlyphScale": true,
                "sliceProjection": false,
                "sliceProjectionUseFiducialColor": true,
                "sliceProjectionOutlinedBehindSlicePlane": false,
                "sliceProjectionColor": [1.0, 1.0, 1.0],
                "sliceProjectionOpacity": 0.6,
                "lineThickness": 0.2,
                "lineColorFadingStart": 1.0,
                "lineColorFadingEnd": 10.0,
                "lineColorFadingSaturation": 1.0,
                "lineColorFadingHueOffset": 0.0,
                "handlesInteractive": false,
                "translationHandleVisibility": true,
                "rotationHandleVisibility": true,
                "scaleHandleVisibility": true,
                "interactionHandleScale": 3.0,
                "snapMode": "toVisibleSurface"
            }
        }
    ]
}